LICENSE
README.md
setup.py
ResifDataTransfer/DataTransfer.py
ResifDataTransfer/ResifDataTransfer.conf.dist
ResifDataTransfer/__init__.py
ResifDataTransfer/__main__.py
ResifDataTransfer/miscTools.py
ResifDataTransfer/rsync.py
ResifDataTransfer/usage.py
ResifDataTransfer.egg-info/PKG-INFO
ResifDataTransfer.egg-info/SOURCES.txt
ResifDataTransfer.egg-info/dependency_links.txt
ResifDataTransfer.egg-info/entry_points.txt
ResifDataTransfer.egg-info/requires.txt
ResifDataTransfer.egg-info/top_level.txt